eabr_functions/__init__.py
eabr_functions/cleansing.py
eabr_functions/databases.py
eabr_functions-2.4.1.dist-info/LICENSE
eabr_functions-2.4.1.dist-info/METADATA
eabr_functions-2.4.1.dist-info/WHEEL
eabr_functions-2.4.1.dist-info/top_level.txt
eabr_functions-2.4.1.dist-info/RECORD
