Metadata-Version: 2.1
Name: eabr-functions
Version: 2.4.1
Summary: EABR Functions
Home-page: https://github.com/walteravelino/eabr-functions
Author: Walter José Avelino da Silva
Author-email: walter.avelin@gmail.com
License: UNKNOWN
Platform: UNKNOWN
Classifier: Programming Language :: Python :: 3
Classifier: License :: OSI Approved :: MIT License
Classifier: Operating System :: OS Independent
License-File: LICENSE
Requires-Dist: botocore
Requires-Dist: psycopg2-binary
Requires-Dist: cx-Oracle
Requires-Dist: pymongo
Requires-Dist: pymssql
